{"dataRough": {"baseInfo": {"carOtherInfo": {"saleType": 0, "blackTagCarTest": false, "testDrive": false, "clueId": 115407582, "minorId": 103860, "minorUrl": "gqjt", "minorName": "广汽集团", "tagId": 162131, "tagUrl": "gqia5", "tagName": "广汽iA5", "storeId": 30255, "carSourceStatus": 0, "productStatus": {"productStatus": 10, "saleMode": 1, "showStatus": 1}, "collectionAbResult": "B", "isNewUser": true, "popUpTime": "5", "remainTime": "10", "stopTime": "8", "newAutoTypeId": 12}, "userLogisticsInfo": {"plateCityId": 12, "receiptCityId": 12, "plateCityName": "北京", "receiptCityName": "北京", "logisticsFree": 0}, "browsingRecords": {"puid": 3014858904, "licenseDate": 2020, "licenseMonth": 3, "roadHaul": 23100, "thumbImg": "https://image1.guazistatic.com/qn211223192117eafa0fba2917f9569db1e34ace4003a2.jpg?imageView2/1/w/190/h/144/q/88"}, "pageOtherInfo": {"ecPilotCity": 1, "consultPhone": "4000696514", "preSellStatus": false, "reserveStatus": false, "saleScene": 1, "exposureStatus": 1, "buyInfoShow": 1}}, "carCommodityInfo": {"basicInfo": {"titleDesc": "广汽集团 广汽iA5 2019款 豪华版", "carLabelList": [{"title": "可迁北京", "popup": {"name": "可迁北京", "text": "登记排放信息符合北京地区迁入政策要求，最终结果以迁入地车管所为准"}, "labelType": 1}, {"title": "维保记录", "popup": {"name": "维保记录", "text": "有正规可查的维修和保养记录"}, "labelType": 6}], "titleTag": "商家", "subTitleTag": "新能源", "tagDesc": "一键下单 车到付款", "imageUrl": "https://image1.guazistatic.com/qn211223192117eafa0fba2917f9569db1e34ace4003a2.jpg?imageView2/1/w/190/h/144/q/88"}, "bannerInfo": {"imageList": [{"category": "车身外观", "images": [{"imgUrl": "https://image1.guazistatic.com/qn211223192117eafa0fba2917f9569db1e34ace4003a2.jpg?imageView2/1/w/750/h/500/q/88", "ind": 1, "thumb": "https://image1.guazistatic.com/qn211223192117eafa0fba2917f9569db1e34ace4003a2.jpg?imageView2/1/w/190/h/144/q/88"}, {"imgUrl": "https://image1.guazistatic.com/qn211223192119314844497c6ac5f5d99277c01d0012a5.jpg?imageView2/1/w/750/h/500/q/88", "ind": 2, "thumb": "https://image1.guazistatic.com/qn211223192119314844497c6ac5f5d99277c01d0012a5.jpg?imageView2/1/w/190/h/144/q/88"}, {"imgUrl": "https://image.guazistatic.com/gz01211223/19/21/3c0d48c5e5f095bc0308377705af2c4f.jpg@base@tag=imgScale&q=88&c=1&w=750&h=500&m=2&q=88&c=1&w=750&h=500&m=2", "ind": 3, "thumb": "https://image.guazistatic.com/gz01211223/19/21/3c0d48c5e5f095bc0308377705af2c4f.jpg@base@tag=imgScale&q=88&c=1&w=190&h=144&m=2&q=88&c=1&w=190&h=144&m=2"}, {"imgUrl": "https://image.guazistatic.com/gz01211223/19/21/95f05930277fd9113c24d66e4c66c13e.jpg@base@tag=imgScale&q=88&c=1&w=750&h=500&m=2&q=88&c=1&w=750&h=500&m=2", "ind": 4, "thumb": "https://image.guazistatic.com/gz01211223/19/21/95f05930277fd9113c24d66e4c66c13e.jpg@base@tag=imgScale&q=88&c=1&w=190&h=144&m=2&q=88&c=1&w=190&h=144&m=2"}, {"imgUrl": "https://image1.guazistatic.com/qn2112231921220c6e19b8d82afb87ca38aa3ae518ca5d.jpg?imageView2/1/w/750/h/500/q/88", "ind": 5, "thumb": "https://image1.guazistatic.com/qn2112231921220c6e19b8d82afb87ca38aa3ae518ca5d.jpg?imageView2/1/w/190/h/144/q/88"}, {"imgUrl": "https://image1.guazistatic.com/qn21122319212387bfd94bd6ef9269afe46ae3b24ee122.jpg?imageView2/1/w/750/h/500/q/88", "ind": 6, "thumb": "https://image1.guazistatic.com/qn21122319212387bfd94bd6ef9269afe46ae3b24ee122.jpg?imageView2/1/w/190/h/144/q/88"}, {"imgUrl": "https://image1.guazistatic.com/qn211223192125b73d50db5029297a71aeef1b9c2c8c07.jpg?imageView2/1/w/750/h/500/q/88", "ind": 7, "thumb": "https://image1.guazistatic.com/qn211223192125b73d50db5029297a71aeef1b9c2c8c07.jpg?imageView2/1/w/190/h/144/q/88"}, {"imgUrl": "https://image1.guazistatic.com/qn211223171719dc63526df49619baad57e48b0c96f6ee.jpg?imageView2/1/w/750/h/500/q/88", "ind": 8, "thumb": "https://image1.guazistatic.com/qn211223171719dc63526df49619baad57e48b0c96f6ee.jpg?imageView2/1/w/190/h/144/q/88"}, {"imgUrl": "https://image1.guazistatic.com/qn2112231717198a330f41275a294e603ca885c840ffeb.jpg?imageView2/1/w/750/h/500/q/88", "ind": 9, "thumb": "https://image1.guazistatic.com/qn2112231717198a330f41275a294e603ca885c840ffeb.jpg?imageView2/1/w/190/h/144/q/88"}, {"imgUrl": "https://image1.guazistatic.com/qn211223171719e668d5422933db1cc711206183f48e52.jpg?imageView2/1/w/750/h/500/q/88", "ind": 10, "thumb": "https://image1.guazistatic.com/qn211223171719e668d5422933db1cc711206183f48e52.jpg?imageView2/1/w/190/h/144/q/88"}, {"imgUrl": "https://image1.guazistatic.com/qn2112231717191a4d473b15cd8ee522dfa881e9eb425a.jpg?imageView2/1/w/750/h/500/q/88", "ind": 34, "thumb": "https://image1.guazistatic.com/qn2112231717191a4d473b15cd8ee522dfa881e9eb425a.jpg?imageView2/1/w/190/h/144/q/88"}, {"imgUrl": "https://image1.guazistatic.com/qn211223171719cb9488b3ca292398dd122ce4db85f8a2.jpg?imageView2/1/w/750/h/500/q/88", "ind": 35, "thumb": "https://image1.guazistatic.com/qn211223171719cb9488b3ca292398dd122ce4db85f8a2.jpg?imageView2/1/w/190/h/144/q/88"}, {"imgUrl": "https://image1.guazistatic.com/qn211223171719b729bdeb22fd3d7a18a9e7df4cf1b4f3.jpg?imageView2/1/w/750/h/500/q/88", "ind": 36, "thumb": "https://image1.guazistatic.com/qn211223171719b729bdeb22fd3d7a18a9e7df4cf1b4f3.jpg?imageView2/1/w/190/h/144/q/88"}, {"imgUrl": "https://image1.guazistatic.com/qn211223171719afc61bec2d324011ef4ec85e927137c8.jpg?imageView2/1/w/750/h/500/q/88", "ind": 37, "thumb": "https://image1.guazistatic.com/qn211223171719afc61bec2d324011ef4ec85e927137c8.jpg?imageView2/1/w/190/h/144/q/88"}, {"imgUrl": "https://image1.guazistatic.com/qn211223171719e470d7e7806c7a09711ababc7f8c098b.jpg?imageView2/1/w/750/h/500/q/88", "ind": 38, "thumb": "https://image1.guazistatic.com/qn211223171719e470d7e7806c7a09711ababc7f8c098b.jpg?imageView2/1/w/190/h/144/q/88"}, {"imgUrl": "https://image1.guazistatic.com/qn211223171719333289a9b341c8549a623d5f26355ead.jpg?imageView2/1/w/750/h/500/q/88", "ind": 39, "thumb": "https://image1.guazistatic.com/qn211223171719333289a9b341c8549a623d5f26355ead.jpg?imageView2/1/w/190/h/144/q/88"}, {"imgUrl": "https://image1.guazistatic.com/qn2112231717195357d39d7982fbf214eb415563b1747a.jpg?imageView2/1/w/750/h/500/q/88", "ind": 40, "thumb": "https://image1.guazistatic.com/qn2112231717195357d39d7982fbf214eb415563b1747a.jpg?imageView2/1/w/190/h/144/q/88"}, {"imgUrl": "https://image1.guazistatic.com/qn211223171719df36630e3e3961763b8c74a7844e3eaf.jpg?imageView2/1/w/750/h/500/q/88", "ind": 43, "thumb": "https://image1.guazistatic.com/qn211223171719df36630e3e3961763b8c74a7844e3eaf.jpg?imageView2/1/w/190/h/144/q/88"}, {"imgUrl": "https://image1.guazistatic.com/qn2112231717199a642d1314bd4fc2a0ee6dae7ec0800a.jpg?imageView2/1/w/750/h/500/q/88", "ind": 46, "thumb": "https://image1.guazistatic.com/qn2112231717199a642d1314bd4fc2a0ee6dae7ec0800a.jpg?imageView2/1/w/190/h/144/q/88"}, {"imgUrl": "https://image1.guazistatic.com/qn211223171719c3a87b211d5a5436d7d37738b8e3ecbd.jpg?imageView2/1/w/750/h/500/q/88", "ind": 48, "thumb": "https://image1.guazistatic.com/qn211223171719c3a87b211d5a5436d7d37738b8e3ecbd.jpg?imageView2/1/w/190/h/144/q/88"}, {"imgUrl": "https://image1.guazistatic.com/qn21122317171988a85b0d141165c879a1dd0eda59dd30.jpg?imageView2/1/w/750/h/500/q/88", "ind": 50, "thumb": "https://image1.guazistatic.com/qn21122317171988a85b0d141165c879a1dd0eda59dd30.jpg?imageView2/1/w/190/h/144/q/88"}, {"imgUrl": "https://image1.guazistatic.com/qn211223171719dbd95d18afdf37c1589df48b8a373f81.jpg?imageView2/1/w/750/h/500/q/88", "ind": 51, "thumb": "https://image1.guazistatic.com/qn211223171719dbd95d18afdf37c1589df48b8a373f81.jpg?imageView2/1/w/190/h/144/q/88"}, {"imgUrl": "https://image1.guazistatic.com/qn211223171719751a5ccd80411b867b7b18e3ee6bb227.jpg?imageView2/1/w/750/h/500/q/88", "ind": 52, "thumb": "https://image1.guazistatic.com/qn211223171719751a5ccd80411b867b7b18e3ee6bb227.jpg?imageView2/1/w/190/h/144/q/88"}, {"imgUrl": "https://image1.guazistatic.com/qn2112231717198bc16946bc99ffcd453400daefe65ece.jpg?imageView2/1/w/750/h/500/q/88", "ind": 53, "thumb": "https://image1.guazistatic.com/qn2112231717198bc16946bc99ffcd453400daefe65ece.jpg?imageView2/1/w/190/h/144/q/88"}, {"imgUrl": "https://image1.guazistatic.com/qn211223171719988c9fb6ebcab71fcfc672c9f60d680d.jpg?imageView2/1/w/750/h/500/q/88", "ind": 54, "thumb": "https://image1.guazistatic.com/qn211223171719988c9fb6ebcab71fcfc672c9f60d680d.jpg?imageView2/1/w/190/h/144/q/88"}, {"imgUrl": "https://image1.guazistatic.com/qn211223171719f632bfa3153b00cb312d28144b7ebe25.jpg?imageView2/1/w/750/h/500/q/88", "ind": 55, "thumb": "https://image1.guazistatic.com/qn211223171719f632bfa3153b00cb312d28144b7ebe25.jpg?imageView2/1/w/190/h/144/q/88"}, {"imgUrl": "https://image1.guazistatic.com/qn21122317171970b4de759695dc08a4fea7fcd5c64335.jpg?imageView2/1/w/750/h/500/q/88", "ind": 56, "thumb": "https://image1.guazistatic.com/qn21122317171970b4de759695dc08a4fea7fcd5c64335.jpg?imageView2/1/w/190/h/144/q/88"}, {"imgUrl": "https://image1.guazistatic.com/qn21122317171979e98afd44a5f5fe70e2bf61e986d903.jpg?imageView2/1/w/750/h/500/q/88", "ind": 57, "thumb": "https://image1.guazistatic.com/qn21122317171979e98afd44a5f5fe70e2bf61e986d903.jpg?imageView2/1/w/190/h/144/q/88"}], "type": 1}, {"category": "中控内饰", "images": [{"imgUrl": "https://image1.guazistatic.com/qn2112231717197b5ec868a1b9ee9131759c450833c262.jpg?imageView2/1/w/750/h/500/q/88", "ind": 11, "thumb": "https://image1.guazistatic.com/qn2112231717197b5ec868a1b9ee9131759c450833c262.jpg?imageView2/1/w/190/h/144/q/88"}, {"imgUrl": "https://image1.guazistatic.com/qn211223171719afef64acf1b09741a5ad70d81b7024e1.jpg?imageView2/1/w/750/h/500/q/88", "ind": 12, "thumb": "https://image1.guazistatic.com/qn211223171719afef64acf1b09741a5ad70d81b7024e1.jpg?imageView2/1/w/190/h/144/q/88"}, {"imgUrl": "https://image1.guazistatic.com/qn211223171719c24712ba809296026da8ba21c2322852.jpg?imageView2/1/w/750/h/500/q/88", "ind": 13, "thumb": "https://image1.guazistatic.com/qn211223171719c24712ba809296026da8ba21c2322852.jpg?imageView2/1/w/190/h/144/q/88"}, {"imgUrl": "https://image1.guazistatic.com/qn211223171719c4365265c3787ee3da45db4de7f3bfc7.jpg?imageView2/1/w/750/h/500/q/88", "ind": 14, "thumb": "https://image1.guazistatic.com/qn211223171719c4365265c3787ee3da45db4de7f3bfc7.jpg?imageView2/1/w/190/h/144/q/88"}, {"imgUrl": "https://image1.guazistatic.com/qn211223171719c5930b756743ac5ff15b2f7cc9351e5b.jpg?imageView2/1/w/750/h/500/q/88", "ind": 15, "thumb": "https://image1.guazistatic.com/qn211223171719c5930b756743ac5ff15b2f7cc9351e5b.jpg?imageView2/1/w/190/h/144/q/88"}, {"imgUrl": "https://image1.guazistatic.com/qn21122317171972c5642be8189bc587cac45e458d18f4.jpg?imageView2/1/w/750/h/500/q/88", "ind": 16, "thumb": "https://image1.guazistatic.com/qn21122317171972c5642be8189bc587cac45e458d18f4.jpg?imageView2/1/w/190/h/144/q/88"}, {"imgUrl": "https://image1.guazistatic.com/qn2112231717194bc90f0f69bda922702f819bd0d941c5.jpg?imageView2/1/w/750/h/500/q/88", "ind": 17, "thumb": "https://image1.guazistatic.com/qn2112231717194bc90f0f69bda922702f819bd0d941c5.jpg?imageView2/1/w/190/h/144/q/88"}, {"imgUrl": "https://image1.guazistatic.com/qn211223171719558355989f764b8c67e84275e8d06737.jpg?imageView2/1/w/750/h/500/q/88", "ind": 18, "thumb": "https://image1.guazistatic.com/qn211223171719558355989f764b8c67e84275e8d06737.jpg?imageView2/1/w/190/h/144/q/88"}, {"imgUrl": "https://image1.guazistatic.com/qn21122317171927e1fce1c970df318206a4245d2bf7dd.jpg?imageView2/1/w/750/h/500/q/88", "ind": 19, "thumb": "https://image1.guazistatic.com/qn21122317171927e1fce1c970df318206a4245d2bf7dd.jpg?imageView2/1/w/190/h/144/q/88"}, {"imgUrl": "https://image1.guazistatic.com/qn2112231717191a20642d498eb142272b497281bc98b9.jpg?imageView2/1/w/750/h/500/q/88", "ind": 20, "thumb": "https://image1.guazistatic.com/qn2112231717191a20642d498eb142272b497281bc98b9.jpg?imageView2/1/w/190/h/144/q/88"}, {"imgUrl": "https://image1.guazistatic.com/qn211223171719e608b83212cd7f197905a0c0bdaffd80.jpg?imageView2/1/w/750/h/500/q/88", "ind": 21, "thumb": "https://image1.guazistatic.com/qn211223171719e608b83212cd7f197905a0c0bdaffd80.jpg?imageView2/1/w/190/h/144/q/88"}, {"imgUrl": "https://image1.guazistatic.com/qn21122317171981af8ba83362b639acb64af1df3b4ca6.jpg?imageView2/1/w/750/h/500/q/88", "ind": 22, "thumb": "https://image1.guazistatic.com/qn21122317171981af8ba83362b639acb64af1df3b4ca6.jpg?imageView2/1/w/190/h/144/q/88"}, {"imgUrl": "https://image1.guazistatic.com/qn211223171719c920cde194302c0f50fc843130f7c00b.jpg?imageView2/1/w/750/h/500/q/88", "ind": 23, "thumb": "https://image1.guazistatic.com/qn211223171719c920cde194302c0f50fc843130f7c00b.jpg?imageView2/1/w/190/h/144/q/88"}, {"imgUrl": "https://image1.guazistatic.com/qn2112231717199ef7fdb3fdfe804e2ab13ca0d400cc15.jpg?imageView2/1/w/750/h/500/q/88", "ind": 41, "thumb": "https://image1.guazistatic.com/qn2112231717199ef7fdb3fdfe804e2ab13ca0d400cc15.jpg?imageView2/1/w/190/h/144/q/88"}, {"imgUrl": "https://image1.guazistatic.com/qn211223171719bec3001f79046d2b786d55e0cc3f70af.jpg?imageView2/1/w/750/h/500/q/88", "ind": 42, "thumb": "https://image1.guazistatic.com/qn211223171719bec3001f79046d2b786d55e0cc3f70af.jpg?imageView2/1/w/190/h/144/q/88"}, {"imgUrl": "https://image1.guazistatic.com/qn21122317171955277fcc090c6267e697fa887c2cc241.jpg?imageView2/1/w/750/h/500/q/88", "ind": 44, "thumb": "https://image1.guazistatic.com/qn21122317171955277fcc090c6267e697fa887c2cc241.jpg?imageView2/1/w/190/h/144/q/88"}, {"imgUrl": "https://image1.guazistatic.com/qn21122317171920b7f287d32e28a7432d730a652ad33b.jpg?imageView2/1/w/750/h/500/q/88", "ind": 45, "thumb": "https://image1.guazistatic.com/qn21122317171920b7f287d32e28a7432d730a652ad33b.jpg?imageView2/1/w/190/h/144/q/88"}, {"imgUrl": "https://image1.guazistatic.com/qn21122317171935c4454b2efae5632ddaa9e8186aa1f4.jpg?imageView2/1/w/750/h/500/q/88", "ind": 47, "thumb": "https://image1.guazistatic.com/qn21122317171935c4454b2efae5632ddaa9e8186aa1f4.jpg?imageView2/1/w/190/h/144/q/88"}, {"imgUrl": "https://image1.guazistatic.com/qn211223171719e0f75280aa5918fc24173a299b9ae823.jpg?imageView2/1/w/750/h/500/q/88", "ind": 49, "thumb": "https://image1.guazistatic.com/qn211223171719e0f75280aa5918fc24173a299b9ae823.jpg?imageView2/1/w/190/h/144/q/88"}], "type": 2}, {"category": "机舱底盘", "images": [{"imgUrl": "https://image1.guazistatic.com/qn211223171719c9f36ce3ff6008f95ce0b950acf1b0ee.jpg?imageView2/1/w/750/h/500/q/88", "ind": 24, "thumb": "https://image1.guazistatic.com/qn211223171719c9f36ce3ff6008f95ce0b950acf1b0ee.jpg?imageView2/1/w/190/h/144/q/88"}, {"imgUrl": "https://image1.guazistatic.com/qn2112231717192b9feee99dd14b42c61c6c0c5932b1de.jpg?imageView2/1/w/750/h/500/q/88", "ind": 25, "thumb": "https://image1.guazistatic.com/qn2112231717192b9feee99dd14b42c61c6c0c5932b1de.jpg?imageView2/1/w/190/h/144/q/88"}, {"imgUrl": "https://image1.guazistatic.com/qn211223171719170cb1964e8a693547625b2bcf195d75.jpg?imageView2/1/w/750/h/500/q/88", "ind": 26, "thumb": "https://image1.guazistatic.com/qn211223171719170cb1964e8a693547625b2bcf195d75.jpg?imageView2/1/w/190/h/144/q/88"}, {"imgUrl": "https://image1.guazistatic.com/qn21122317171911cf582999fe1b776b537f24d5b0e5e1.jpg?imageView2/1/w/750/h/500/q/88", "ind": 27, "thumb": "https://image1.guazistatic.com/qn21122317171911cf582999fe1b776b537f24d5b0e5e1.jpg?imageView2/1/w/190/h/144/q/88"}, {"imgUrl": "https://image1.guazistatic.com/qn2112231717195642a22c05b2f9e885bf5b7a64ee950c.jpg?imageView2/1/w/750/h/500/q/88", "ind": 28, "thumb": "https://image1.guazistatic.com/qn2112231717195642a22c05b2f9e885bf5b7a64ee950c.jpg?imageView2/1/w/190/h/144/q/88"}, {"imgUrl": "https://image1.guazistatic.com/qn2112231717199bd54ea9fc6338b23d15a9f0988cb25e.jpg?imageView2/1/w/750/h/500/q/88", "ind": 30, "thumb": "https://image1.guazistatic.com/qn2112231717199bd54ea9fc6338b23d15a9f0988cb25e.jpg?imageView2/1/w/190/h/144/q/88"}, {"imgUrl": "https://image1.guazistatic.com/qn2112231717191181487502d91f3e4ec191af5ff6bf65.jpg?imageView2/1/w/750/h/500/q/88", "ind": 29, "thumb": "https://image1.guazistatic.com/qn2112231717191181487502d91f3e4ec191af5ff6bf65.jpg?imageView2/1/w/190/h/144/q/88"}], "type": 3}], "videoList": []}, "carPriceInfo": {"styleType": 2, "styleData": {"priceTitle": "售价", "price": {"value": 116800, "priceDes": "11.68", "unit": "万"}, "newPrice": {"value": 198423, "priceDes": "19.84", "unit": "万"}}, "showPrice": "11.68万"}, "carRecordInfo": {"baseInfo": {"clueIdStr": "车源号HC-115407582", "carId": 193114, "puId": 3014858904, "newEv": true, "carRecordAb": "B"}, "reportResultAnalysis": {"complex": "9成新", "outLook": "8成新", "inter": "9成新", "machine": "9成新", "taskId": "3770102"}, "salienceItem": [{"label": "首次上牌", "value": "2020-03"}, {"label": "表显里程", "value": "2.3万公里"}, {"label": "排放标准", "value": "新能源", "gray": true}], "summary": [{"label": "过户次数", "value": "2次"}, {"label": "总功率", "value": "135kW"}, {"label": "车牌归属地", "value": "东莞(粤)"}, {"label": "续航里程", "value": "510km", "popStruct": {"title": "续航里程提示", "desc": "标示的续航里程为工信部公示的新车纯电续航里程（NEDC），不代表本车辆的实际续航里程。"}}, {"label": "年检到期", "value": "2022-03"}, {"label": "电池容量", "value": "58kWh"}, {"label": "交强险到期", "value": "2022-06"}, {"label": "使用性质", "value": "非营运"}, {"label": "车身颜色", "value": "白色"}, {"label": "出厂日期", "value": "2019-12"}, {"label": "车源号", "value": "115407582"}, {"label": "钥匙数量", "value": "2把"}], "maintenance": "2次保养", "maintenanceAbString": "B", "highlightConfigItem": [{"id": 15, "title": "运动风格座椅", "image": "https://image1.guazistatic.com/qn2105181218522f4d8cc8172c88b8b7ab29b81399e398.png", "desc": "专门针对人体动态设计，两侧的腰部/肩部以及背部能够有良好的侧向支撑性。"}, {"id": 18, "title": "全液晶仪表盘", "image": "https://image1.guazistatic.com/qn21051812221834e55c80d3e816e3554430695337df3a.png", "desc": "液晶屏替代机械仪表,信息更丰富,感官体验更先进。"}, {"id": 36, "title": "自动驻车", "image": "https://image1.guazistatic.com/qn2105181248157f6ce42b6e813cc93f9b2b7262273ca6.png", "desc": "AUTO HOLD 适用于上下坡以及频繁起步停车时，既省去切换档位又减少“溜车\"现象。"}, {"id": 43, "title": "座椅电动调节", "image": "https://image1.guazistatic.com/qn21051813115658fb2c89a7f5dc7fd354d2bb4af37474.png", "desc": "相对于手动调节。根据调节方向，可分为前后、高低等，可调方向数和部位越复杂，配置和价格越高。"}, {"id": 44, "title": "自动头灯", "image": "https://image1.guazistatic.com/qn21051813000667976dbaca483c2fb701df51f3b0002e.png", "desc": "行驶中光线变暗，前大灯会自动亮起，如进入地库，天刚刚黑时。减低视线不良造成的危险。"}, {"id": 46, "title": "无钥匙启动", "image": "https://image1.guazistatic.com/qn2105181302057f268fb7d73f173f1bed5354cb48a986.png", "desc": "钥匙在身上时，按下车内按键或拧动旋钮即可使发动机点火，使用更加便捷。"}, {"id": 47, "title": "后排出风口", "image": "https://image1.guazistatic.com/qn21051813030855b75541364d83c2da87590c759c8a04.png", "desc": "为后排设计的空调出风口，解决空调冷热不均问题。置于前中央扶手后，也有置于B柱的。"}, {"id": 48, "title": "胎压监测", "image": "https://image1.guazistatic.com/qn2105181304244993a3a1f53e20e4b692d87b4916f67b.png", "desc": "对轮胎漏气和低气压进行报警，以确保行车安全。"}, {"id": 49, "title": "蓝牙/车载电话", "image": "https://image1.guazistatic.com/qn210518130527ef43f30c8983111b9c54f0ca72595777.png", "desc": "通过车内蓝牙链接手机蓝牙，一键接打，提升安全性和舒适性。"}, {"id": 51, "title": "上坡辅助", "image": "https://image1.guazistatic.com/qn210518130747b6121bb3bccf0428f11870cadfab9c9a.png", "desc": "ESP衍生出的安全配置，可有效避免在坡道上起步溜车的情况。"}, {"id": 52, "title": "倒车雷达", "image": "https://image1.guazistatic.com/qn2105181309017fba099c9f5126ad4515e996c8681fe2.png", "desc": "泊车或慢速行驶时探测障碍物，减少因视线不良而引起的碰撞、刮蹭事故的可能。"}, {"id": 53, "title": "车窗防夹手", "image": "https://image1.guazistatic.com/qn2105181310058f616ca174136134e26bab1779cf283f.png", "desc": "电动车窗关闭时，遇到阻力后会自动停止上升，也有的改变为玻璃下降，防止夹伤乘员。"}]}, "carImageOutShow": [{"key": "surface", "desc": "外观", "imageIndList": [1, 2, 3]}, {"key": "interior", "desc": "内饰", "imageIndList": [20, 21]}, {"key": "centralControl", "desc": "中控", "imageIndList": [12]}]}, "buyInfo": {"financeInfo": {"isPay": 1, "title": "分期", "description": "首付3.60万起", "firstPayDesc": "3.60万", "activityDescription": "限时免收1750元", "activityDescriptionV1": "限时特惠分期购车立减1750元", "linkUrl": "https://uc.guazi.com/confirm-info/calculator/?clueId=115407582&hideTitlebar=1&onlyFinance=1", "userCreditDesc": 0}, "serviceGuarantee": {"button": "售后", "content": [{"key": "tui_fix", "title": "不满意退全款", "tips": "不喜欢就退车，全额退款", "popup": {"name": "试7天不满意退全款", "text": "收到车后您可充分体验车辆的驾驶感受，如有任何不满，满足相应条件，可享受“试7天不满意退全款”保障，退还所支付的车款、物流费、落档费。"}, "graranteeType": "AFTER_SALE", "text": "7天无理由退车", "icon": "https://image.guazistatic.com/gz01191202/19/35/261518d01698ba05cbe4cb821a3e4fd9.png", "eventId": "901545647592", "newIcon": "https://image1.guazistatic.com/qn191227114324c2afdb62a5f316be9aad9f55bef6fc7e.png", "gifIcon": "https://image1.guazistatic.com/qn191227170515f1a34d30ff502dd579ac7bc45abf5b28.gif"}], "carType": 1, "blackTagCarTest": false, "saleType": 0}, "rankingInfo": {}}, "productCenterAb": "B"}, "dataDetail": {"list": [{"id": 1, "title": "基本参数", "supportOptional": false, "children": [{"id": 1, "title": "厂商", "content": "广汽丰田"}, {"id": 2, "title": "生产方式", "content": "国产"}, {"id": 3, "title": "厂商指导价(万元)", "content": "18.28"}, {"id": 4, "title": "上市时间", "content": "2019.09"}, {"id": 5, "title": "能源形式", "content": "纯电动"}, {"id": 9, "title": "工信部纯电续航里程(km)", "content": "510"}, {"id": 10, "title": "车身形式", "content": "4门5座三厢车"}]}, {"id": 3, "title": "电动机", "supportOptional": true, "children": [{"id": 1, "title": "电机类型", "standardGroup": [{"content": "永磁 "}, {"content": " 同步"}]}, {"id": 2, "title": "电动机总功率(kW)", "content": "135"}, {"id": 3, "title": "电动机总扭矩(N·m)", "content": "300"}, {"id": 4, "title": "前电动机最大功率(kW)", "content": "135"}, {"id": 5, "title": "前电动机最大扭矩(N·m)", "content": "300"}, {"id": 10, "title": "驱动电机数", "content": "单电机"}, {"id": 11, "title": "电机数", "content": "前置"}, {"id": 12, "title": "电池类型", "content": "三元锂电池"}, {"id": 13, "title": "工信部续航里程(km)", "content": "510"}, {"id": 14, "title": "百公里耗电量(kWh/100km)", "content": "13.1"}, {"id": 15, "title": "电池组质保(生产厂商)", "content": "八年或15万公里"}, {"id": 16, "title": "电池容量", "content": "58.8"}, {"id": 17, "title": "快充时间(小时)", "content": "0.57"}, {"id": 18, "title": "慢充时间(小时)", "content": "9.5"}, {"id": 19, "title": "快充电量(%)", "content": "80"}]}, {"id": 4, "title": "变速箱", "supportOptional": false, "children": [{"id": 1, "title": "变速箱类型", "content": "自动"}, {"id": 3, "title": "变速器描述", "content": "固定齿比变速箱"}, {"id": 4, "title": "挡位个数", "content": "1"}]}, {"id": 5, "title": "车身结构", "supportOptional": false, "children": [{"id": 1, "title": "轴距(mm)", "content": "2750"}, {"id": 2, "title": "长度(mm)", "content": "4792"}, {"id": 3, "title": "宽度(mm)", "content": "1880"}, {"id": 4, "title": "高度(mm)", "content": "1530"}, {"id": 8, "title": "车门数(个)", "content": "4门"}, {"id": 9, "title": "座位数(个)", "content": "5"}, {"id": 11, "title": "行李厢容积(L)", "content": "453"}, {"id": 14, "title": "整备质量(kg)", "content": "1625"}]}, {"id": 6, "title": "底盘转向", "supportOptional": false, "children": [{"id": 1, "title": "驱动方式", "content": "前置前驱"}, {"id": 4, "title": "前悬架类型", "content": "麦弗逊式独立悬架"}, {"id": 5, "title": "后悬架类型", "content": "扭力梁式非独立悬架"}, {"id": 6, "title": "前制动器类型", "content": "通风盘式"}, {"id": 7, "title": "后制动器类型", "content": "盘式"}, {"id": 8, "title": "转向助力类型", "content": "电动助力"}, {"id": 9, "title": "车体结构", "content": "承载式"}, {"id": 10, "title": "驻车制动类型", "content": "电子驻车"}, {"id": 11, "title": "前轮胎规格", "content": "215/55 R17"}, {"id": 12, "title": "后轮胎规格", "content": "215/55 R17"}]}, {"id": 7, "title": "安全配置", "supportOptional": true, "children": [{"id": 1, "title": "驾驶座安全气囊", "isStandard": 1}, {"id": 2, "title": "副驾驶安全气囊", "isStandard": 1}, {"id": 3, "title": "前排侧气囊", "isStandard": 1}, {"id": 5, "title": "前排头部气囊(气帘)", "isStandard": 1}, {"id": 6, "title": "后排头部气囊(气帘)", "isStandard": 1}, {"id": 8, "title": "胎压监测装置", "isStandard": 1}, {"id": 10, "title": "ISOFIX儿童座椅接口", "isStandard": 1}, {"id": 11, "title": "ABS防抱死", "isStandard": 1}, {"id": 12, "title": "制动力分配(EBD/CBC等)", "isStandard": 1}, {"id": 13, "title": "刹车辅助(EBA/BAS/BA等)", "isStandard": 1}, {"id": 14, "title": "牵引力控制(ASR/TCS/TRC等)", "isStandard": 1}, {"id": 15, "title": "车身稳定控制(ESC/ESP/DSC等)", "isStandard": 1}]}, {"id": 8, "title": "辅助操控配置", "supportOptional": true, "children": [{"id": 8, "title": "倒车雷达", "isStandard": 1}, {"id": 16, "title": "自动驻车", "isStandard": 1}, {"id": 18, "title": "上坡辅助", "isStandard": 1}]}, {"id": 9, "title": "外部配置", "supportOptional": true, "children": [{"id": 11, "title": "车内中控锁", "isStandard": 1}, {"id": 13, "title": "无钥匙启动系统", "isStandard": 1}]}, {"id": 10, "title": "内部配置", "supportOptional": true, "children": [{"id": 3, "title": "多功能方向盘", "isStandard": 1}, {"id": 9, "title": "全液晶仪表盘", "isStandard": 1}, {"id": 11, "title": "全液晶仪表盘", "isStandard": 1}]}, {"id": 11, "title": "座椅配置", "supportOptional": true, "children": [{"id": 2, "title": "运动风格座椅", "isStandard": 1}, {"id": 6, "title": "主座椅电动调节", "isStandard": 1}, {"id": 19, "title": "前/后中央扶手", "standardGroup": [{"text": "前", "isStandard": 1}, {"text": "后", "isStandard": 1}]}, {"id": 20, "title": "后排杯架", "isStandard": 1}]}, {"id": 12, "title": "多媒体配置", "supportOptional": true, "children": [{"id": 2, "title": "GPS导航系统", "isStandard": 1}, {"id": 4, "title": "蓝牙/车载电话", "isStandard": 1}, {"id": 6, "title": "车联网", "isStandard": 1}]}, {"id": 13, "title": "灯光配置", "supportOptional": true, "children": [{"id": 4, "title": "日间行车灯", "isStandard": 1}, {"id": 6, "title": "自动头灯", "isStandard": 1}, {"id": 10, "title": "大灯高度可调", "isStandard": 1}]}, {"id": 14, "title": "玻璃/后视镜", "supportOptional": true, "children": [{"id": 1, "title": "前电动车窗", "isStandard": 1}, {"id": 2, "title": "后电动车窗", "isStandard": 1}, {"id": 3, "title": "车窗防夹手功能", "isStandard": 1}]}, {"id": 15, "title": "空调/冰箱", "supportOptional": true, "children": [{"id": 3, "title": "后座出风口", "isStandard": 1}, {"id": 4, "title": "温度分区控制", "isStandard": 1}]}]}}